taupy/__init__.py
taupy/app.py
taupy/cli/__init__.py
taupy/cli/commands/__init__.py
taupy/cli/commands/build.py
taupy/cli/commands/config.py
taupy/cli/commands/dev.py
taupy/cli/commands/doctor.py
taupy/cli/commands/info.py
taupy/cli/commands/new.py
taupy/cli/main.py
taupy/cli/version.py
taupy/devui.py
taupy/dispatcher.py
taupy/events/__init__.py
taupy/events/events.py
taupy/reloader.py
taupy/router.py
taupy/server.py
taupy/state.py
taupy/templates/base.html
taupy/templates/vanilla/dist/index.html
taupy/templates/vanilla/dist/main.js
taupy/templates/vanilla/dist/style.css
taupy/templates/vite-react/.gitignore
taupy/templates/vite-react/eslint.config.js
taupy/templates/vite-react/index.html
taupy/templates/vite-react/package.json
taupy/templates/vite-react/public/vite.svg
taupy/templates/vite-react/README.md
taupy/templates/vite-react/src/App.css
taupy/templates/vite-react/src/App.tsx
taupy/templates/vite-react/src/assets/react.svg
taupy/templates/vite-react/src/index.css
taupy/templates/vite-react/src/main.tsx
taupy/templates/vite-react/src/taupyClient.ts
taupy/templates/vite-react/tsconfig.app.json
taupy/templates/vite-react/tsconfig.json
taupy/templates/vite-react/tsconfig.node.json
taupy/templates/vite-react/vite.config.ts
taupy/theme.py
taupy/utils/client.js
taupy/utils/taupy.exe
taupy/utils/template.py
taupy/utils/template_react.py
taupy/utils/template_vanilla.py
taupy/utils/WebView2Loader.dll
taupy/var.py
taupy/widgets/__init__.py
taupy/widgets/component.py
taupy/widgets/elements.py
taupy/widgets/factory.py
taupy/widgets/layout.py
taupy/window/build.rs
taupy/window/Cargo.toml
taupy/window/src/api.rs
taupy/window/src/config.rs
taupy/window/src/main.rs
taupy/window/src/server.rs
taupy/window/src/window.rs
taupy_framework-0.0.5.dist-info/entry_points.txt
taupy_framework-0.0.5.dist-info/LICENSE
taupy_framework-0.0.5.dist-info/METADATA
taupy_framework-0.0.5.dist-info/WHEEL
taupy_framework-0.0.5.dist-info/RECORD
