Metadata-Version: 2.1
Name: taupy-framework
Version: 0.0.5
Summary: TauPy Framework
Author: S1avv
Requires-Python: >=3.10,<3.12
Classifier: Programming Language :: Python :: 3
Classifier: Programming Language :: Python :: 3.10
Classifier: Programming Language :: Python :: 3.11
Provides-Extra: system
Requires-Dist: click (>=8.1.8,<9.0.0)
Requires-Dist: nuitka (>=2.8.6,<3.0.0)
Requires-Dist: packaging (>=25.0,<26.0)
Requires-Dist: psutil (>=5.9.8,<7.0) ; extra == "system"
Requires-Dist: pytest (==9.0.0)
Requires-Dist: requests (>=2.32.5,<3.0.0)
Requires-Dist: watchfiles (>=1.1.1,<2.0.0)
Requires-Dist: websockets (>=12.0,<13.0)
